live_radio/__init__.py
live_radio/radio.py
live_radio-0.1.0.dist-info/licenses/LICENSE
live_radio-0.1.0.dist-info/METADATA
live_radio-0.1.0.dist-info/WHEEL
live_radio-0.1.0.dist-info/top_level.txt
live_radio-0.1.0.dist-info/RECORD
